anime_parsers_ru/__init__.py
anime_parsers_ru/api_kodik.py
anime_parsers_ru/errors.py
anime_parsers_ru/internal_tools.py
anime_parsers_ru/parser_aniboom.py
anime_parsers_ru/parser_aniboom_async.py
anime_parsers_ru/parser_jutsu.py
anime_parsers_ru/parser_kodik.py
anime_parsers_ru/parser_kodik_async.py
anime_parsers_ru/parser_shikimori.py
anime_parsers_ru/parser_shikimori_async.py
anime_parsers_ru-1.13.2.dist-info/licenses/LICENSE
anime_parsers_ru-1.13.2.dist-info/METADATA
anime_parsers_ru-1.13.2.dist-info/WHEEL
anime_parsers_ru-1.13.2.dist-info/top_level.txt
anime_parsers_ru-1.13.2.dist-info/RECORD
