Metadata-Version: 2.4
Name: anime_parsers_ru
Version: 1.13.2
Summary: Python package for parsing russian anime players
Author-email: YaNesyTortiK <ya.nesy.tortik.email@gmail.com>
Maintainer-email: YaNesyTortiK <ya.nesy.tortik.email@gmail.com>
Project-URL: Homepage, https://github.com/YaNesyTortiK/AnimeParsers
Project-URL: Issues, https://github.com/YaNesyTortiK/AnimeParsers/issues
Keywords: anime,parser,kodik,parsing,aniboom,animego,jutsu,shikimori,kodikapi,kodik api,аниме,парсинг,кодик,парсер,анибум,анимего,джутсу,шикимори,кодик апи
Classifier: Development Status :: 4 - Beta
Classifier: Programming Language :: Python :: 3
Classifier: Operating System :: OS Independent
Requires-Python: >=3.10
License-File: LICENSE
Requires-Dist: beautifulsoup4>=4.12
Requires-Dist: requests>=2.32
Provides-Extra: async
Requires-Dist: aiohttp>=3.9.5; extra == "async"
Provides-Extra: lxml
Requires-Dist: lxml>=5.2; extra == "lxml"
Dynamic: license-file
